development.ini
fassembler_config.ini_tmpl
regen-docs
setup.cfg
setup.py
test
ScriptTranscluder.egg-info/PKG-INFO
ScriptTranscluder.egg-info/SOURCES.txt
ScriptTranscluder.egg-info/dependency_links.txt
ScriptTranscluder.egg-info/entry_points.txt
ScriptTranscluder.egg-info/not-zip-safe
ScriptTranscluder.egg-info/requires.txt
ScriptTranscluder.egg-info/top_level.txt
docs/conf.py
docs/index.txt
docs/example-pages/index.html
scripttranscluder/__init__.py
scripttranscluder/app.py
scripttranscluder/wsgiapp.py
tests/__init__.py
tests/test_transcluder.py