Metadata-Version: 1.0
Name: ScriptTranscluder
Version: 0.2
Summary: Transclude content via <script> tags
Home-page: http://pypi.python.org/pypi/ScriptTranscluder
Author: Ian Bicking
Author-email: ianb@openplans.org
License: GPL
Keywords: tranclude web application javascript
Platform: UNKNOWN
Classifier: Development Status :: 4 - Beta
Classifier: Framework :: Paste
Classifier: Intended Audience :: Developers
Classifier: License :: OSI Approved :: GNU General Public License (GPL)
Classifier: Topic :: Internet :: WWW/HTTP :: WSGI
Classifier: Topic :: Internet :: WWW/HTTP :: WSGI :: Application
Classifier: Topic :: Text Processing :: Markup :: HTML
